wbutil/__init__.py
wbutil/coroutine.py
wbutil/fs.py
wbutil/func.py
wbutil/misc.py
wbutil/pipeline.py
wbutil/queue.py
wbutil/math/__init__.py
wbutil/math/naivebayes.py
wbutil/math/stat.py
wbutil/math/tree.py
wbutil-2.0.2a0.dist-info/DESCRIPTION.rst
wbutil-2.0.2a0.dist-info/METADATA
wbutil-2.0.2a0.dist-info/RECORD
wbutil-2.0.2a0.dist-info/WHEEL
wbutil-2.0.2a0.dist-info/metadata.json
wbutil-2.0.2a0.dist-info/top_level.txt
