Metadata-Version: 2.0
Name: wbutil
Version: 2.0.2a0
Summary: Python utility library
Home-page: https://github.com/wbadart/wbutil-py
Author: Will Badart
Author-email: wbadart@live.com
License: MIT
Project-URL: Bug Tracker, https://github.com/wbadart/wbutil-py/issues
Project-URL: Documentation, https://github.com/wbadart/wbutil-py/wiki
Project-URL: Source Code, https://github.com/wbadart/wbutil-py
Keywords: utility util helper library
Platform: UNKNOWN
